mlbands/ML.py
mlbands/__init__.py
mlbands/main.py
mlbands/misc.py
mlbands/neuralnets/__init__.py
mlbands/neuralnets/lenet3d.py
mlbands/neuralnets/lenet5.py
mlbands-1.0.1.dist-info/METADATA
mlbands-1.0.1.dist-info/WHEEL
mlbands-1.0.1.dist-info/RECORD
