Metadata-Version: 2.1
Name: mlbands
Version: 1.0.1
Summary: A Python package that implements automatic prediction of electronic band gaps for a set of materials based on training data
Author: Andrew R. Garcia
Requires-Python: >=3.8,<4.0
Classifier: Programming Language :: Python :: 3
Classifier: Programming Language :: Python :: 3.8
Classifier: Programming Language :: Python :: 3.9
Classifier: Programming Language :: Python :: 3.10
Classifier: Programming Language :: Python :: 3.11
Requires-Dist: mp-api (>=0.30.5,<0.31.0)
Requires-Dist: torch (>=1.13.1,<2.0.0)
Requires-Dist: torchvision (>=0.14.1,<0.15.0)
